metrics_accumulator_client/Client.py
metrics_accumulator_client/__init__.py
metrics_accumulator_client-1.1.5.dist-info/METADATA
metrics_accumulator_client-1.1.5.dist-info/WHEEL
metrics_accumulator_client-1.1.5.dist-info/RECORD
