Metadata-Version: 2.3
Name: metrics-accumulator-client
Version: 1.1.5
Summary: This is the python client for metrics accumulator
Project-URL: Documentaion, https://github.com/bpoole6/metrics-accumulator-clients/tree/main/python-client
Project-URL: Source code, https://github.com/bpoole6/metrics-accumulator-clients/tree/main/python-client
Author-email: Austin Poole <readblip@yahoo.com>
Maintainer-email: Austin Poole <readblip@yahoo.com>
License-Expression: Apache-2.0 OR MIT
Keywords: client,metrics-accumulator,prometheus
Requires-Python: >=3.8
Requires-Dist: prometheus-client>=0.16.0
Requires-Dist: requests>=2.25.1
